docker_compose_postgres/__init__.py
docker_compose_postgres-0.0.2.dist-info/LICENSE
docker_compose_postgres-0.0.2.dist-info/METADATA
docker_compose_postgres-0.0.2.dist-info/WHEEL
docker_compose_postgres-0.0.2.dist-info/entry_points.txt
docker_compose_postgres-0.0.2.dist-info/top_level.txt
docker_compose_postgres-0.0.2.dist-info/RECORD
