Metadata-Version: 2.1
Name: docker-compose-postgres
Version: 0.0.2
Summary: Simplify work with postgres inside docker-compose service
Home-page: https://github.com/d10xa/docker-compose-postgres
Author: d10xa
Author-email: d10xa@mail.ru
License: MIT
Platform: UNKNOWN
Classifier: License :: OSI Approved :: MIT License
Classifier: Programming Language :: Python :: 2
Classifier: Programming Language :: Python :: 3
Requires-Dist: pyyaml
